{
  "201010": "\tUsing Items\r",
  "201100": "\tWielding Armaments\r",
  "301020": "\tSites of Grace\r",
  "301060": "\tSorceries and Incantations\r",
  "301130": "\tBows\r",
  "301140": "\tCrouching\r",
  "301160": "\tStance-Breaking\r",
  "301500": "\tThe Map\r",
  "301510": "\tGuidance of Grace\r",
  "301520": "\tHorseback Riding\r",
  "301530": "\tDeath\r",
  "301540": "\tStakes of Marika\r",
  "301550": "\tSummoning Spirits\r",
  "301560": "\tMaterials\r",
  "301570": "\tItem Crafting\r",
  "301580": "\tContainers\r",
  "301590": "\tFlask of Wondrous Physick\r",
  "301600": "\tAdding Skills\r",
  "301610": "\tBirdseye Telescopes\r",
  "301620": "\tSpiritspring Jumping\r",
  "301630": "\tVanquishing Enemy Groups\r",
  "301640": "\tTeardrop Scarabs\r",
  "301650": "\tSummoning Other Players\r",
  "301660": "\tCooperative Multiplayer\r",
  "301670": "\tCompetitive Multiplayer\r",
  "301680": "\tInvasion Multiplayer\r",
  "301690": "\tSummoning Pools\r",
  "302000": "\tAdding Affinities\r",
  "302380": "\tHunter Multiplayer\r",
  "302390": "\tMonument Icon\r",
  "302400": "\tGuard Counters\r",
  "302410": "\tGuarding\r",
  "302420": "\tRequesting Aid from a Hunter\r",
  "302430": "\tSkills\r",
  "302440": "\tFast Travel to Sites of Grace\r",
  "302450": "\tStrengthening Armaments\r",
  "302460": "\tRoundtable Hold\r",
  "302470": "\tDense Fog of Sleep\r",
  "302480": "\tPouches\r",
  "302490": "\tDodging\r",
  "302500": "\tGreat Runes\r",
  "302510": "\tThe Cave of Knowledge\r",
  "302550": "\tDuels\r",
  "302560": "\tUnited Combat and Combat Ordeals\r",
  "302570": "\tCombat with Spirit Ashes\r",
  "302580": "\tMarika's Effigy at the Roundtable\r",
  "309000": "\tMultiplayer\r",
  "402000": "\tEquipment Menu\r",
  "402010": "\tItem Crafting Menu\r",
  "402020": "\tInventory Menu\r",
  "402030": "\tStatus Menu\r",
  "402040": "\tMessage Menu\r",
  "402050": "\tMultiplayer Menu\r",
  "402100": "\tMap Menu\r",
  "402200": "\tLevel Up Menu\r",
  "402210": "\tMenu: Additional Healing Flasks\r",
  "402220": "\tMenu: Increasing Healing Amount\r",
  "402230": "\tAllocating Flask Uses\r",
  "402240": "\tMemorize Spells Menu\r",
  "402250": "\tSorting the Chest\r",
  "402300": "\tShop Menu\r",
  "402310": "\tMenu: Weapon Upgrades\r",
  "402320": "\tAshes of War Menu\r",
  "402330": "\tSpirit Tuning Menu\r",
  "402340": "\tMenu: Dragon Communion Shop\r",
  "402350": "\tGreat Rune Menu\r",
  "402360": "\tMixing Physicks\r",
  "402370": "\tRebirth Menu\r",
  "402380": "\tPower of Remembrance Menu\r",
  "402390": "\tSmithing Menu\r",
  "402400": "\tRemembrance Duplication Menu\r",
  "402500": "\tColosseum Menu\r",
  "": ""
}
