{
  "1": "\tなし\r",
  "10": "\t戦技なし\r",
  "100": "\t獅子斬り\r",
  "101": "\t貫通突き\r",
  "102": "\t牙突き\r",
  "103": "\t回転斬り\r",
  "104": "\t回転薙ぎ\r",
  "105": "\t突撃\r",
  "106": "\t踏み込み（斬り上げ）\r",
  "107": "\t踏み込み（回転薙ぎ）\r",
  "108": "\t血の徴収\r",
  "109": "\t連続突き\r",
  "110": "\t乱撃\r",
  "111": "\t回転撃\r",
  "112": "\t二連斬り\r",
  "113": "\t司教の突進\r",
  "114": "\t居合\r",
  "115": "\t構え\r",
  "116": "\t巨人狩り\r",
  "117": "\t松明攻撃\r",
  "118": "\tローレッタの斬撃\r",
  "119": "\t毒蛾は二度舞う\r",
  "120": "\t回れ回れ\r",
  "122": "\t嵐の襲撃\r",
  "123": "\t嵐呼び\r",
  "124": "\t剣舞\r",
  "125": "\t鎖回し\r",
  "200": "\t輝剣の円陣\r",
  "201": "\t聖なる刃\r",
  "202": "\t氷槍\r",
  "203": "\t輝石のつぶて\r",
  "204": "\t血の斬撃\r",
  "205": "\t命奪拳\r",
  "207": "\t溶岩噴火\r",
  "208": "\t祈りの一撃\r",
  "209": "\tグラビタス\r",
  "210": "\t嵐の刃\r",
  "212": "\t地揺らし\r",
  "213": "\t黄金の地\r",
  "214": "\t炎撃\r",
  "216": "\t落雷\r",
  "217": "\t雷撃斬\r",
  "218": "\tグレート・カーリア\r",
  "219": "\tカーリアの大剣\r",
  "220": "\t真空斬り\r",
  "221": "\t黒炎の渦\r",
  "222": "\t聖なる光輪\r",
  "223": "\t火吹き\r",
  "224": "\t血の刃\r",
  "225": "\t共撃の幻\r",
  "226": "\t幻影の槍\r",
  "227": "\t冷気の霧\r",
  "228": "\t毒の霧\r",
  "300": "\tシールドバッシュ\r",
  "301": "\t鉄壁の盾\r",
  "302": "\tパリィ\r",
  "303": "\tバックラーパリィ\r",
  "304": "\tパリィ\r",
  "305": "\tカーリアの返報\r",
  "306": "\t嵐の壁\r",
  "307": "\t黄金パリィ\r",
  "308": "\t突撃バッシュ\r",
  "309": "\tトープスの力場\r",
  "400": "\t貫通射撃\r",
  "401": "\t連続射撃\r",
  "402": "\t強射\r",
  "404": "\t宿し撃ち\r",
  "405": "\t空撃ち\r",
  "406": "\tアローレイン\r",
  "407": "\t不可視の矢\r",
  "501": "\t霜踏み\r",
  "502": "\t嵐脚\r",
  "503": "\tキック\r",
  "504": "\t雷の羊\r",
  "505": "\t赤獅子の炎\r",
  "506": "\tヒップドロップ\r",
  "507": "\t黄金の尻撃\r",
  "508": "\t暗黒波\r",
  "509": "\tホーラ・ルーの地揺らし\r",
  "600": "\tデターミネーション\r",
  "601": "\t王騎士の決意\r",
  "602": "\t暗殺の作法\r",
  "603": "\t黄金樹に誓って\r",
  "604": "\t聖律\r",
  "605": "\t聖律共有\r",
  "606": "\t切腹\r",
  "607": "\t岩石剣\r",
  "650": "\t野蛮な咆哮\r",
  "651": "\tウォークライ\r",
  "652": "\t獣の咆哮\r",
  "653": "\tトロルの咆哮\r",
  "654": "\t誇示する咆哮\r",
  "700": "\t我慢\r",
  "701": "\t無敵\r",
  "702": "\t聖域\r",
  "800": "\tクイックステップ\r",
  "801": "\t猟犬のステップ\r",
  "802": "\t霧の猛禽\r",
  "850": "\t白い影の誘い\r",
  "1000": "\t噴き上がる信仰\r",
  "1001": "\t炎の唾\r",
  "1002": "\t火炎舌\r",
  "1003": "\t神託のシャボン\r",
  "1004": "\t降り注ぐシャボン\r",
  "1005": "\t神託の大シャボン\r",
  "1006": "\t溶岩の海\r",
  "1007": "\t毒蛇の噛みつき\r",
  "1008": "\t月光剣\r",
  "1009": "\tシルリアの渦\r",
  "1010": "\t軍旗の下に\r",
  "1011": "\tご照覧あれい！\r",
  "1012": "\tエオヒドの剣舞\r",
  "1013": "\t霊障招き\r",
  "1014": "\t略奪の炎\r",
  "1015": "\tミエロスの絶叫\r",
  "1016": "\tレドゥビアの血刃\r",
  "1017": "\t輝石の彗礫\r",
  "1018": "\t流体化\r",
  "1019": "\t夜と炎の構え\r",
  "1020": "\t黄金波\r",
  "1021": "\t滅びの霊炎\r",
  "1022": "\t黄金律掲揚\r",
  "1023": "\t眠りの霧\r",
  "1024": "\t槍呼びの儀\r",
  "1025": "\t狼の襲撃\r",
  "1026": "\t雷雲の姿\r",
  "1027": "\t呪血の斬撃\r",
  "1028": "\t水鳥乱舞\r",
  "1029": "\t黄金砕き\r",
  "1030": "\t地に伏せよ！\r",
  "1031": "\t王の雄叫び\r",
  "1032": "\t星呼び\r",
  "1033": "\t崩壊波\r",
  "1034": "\t血授の儀\r",
  "1035": "\t流体化\r",
  "1036": "\t死の刃\r",
  "1037": "\t黄金の刃\r",
  "1038": "\t運命の死\r",
  "1039": "\t車輪回転\r",
  "1040": "\t白王の引力波\r",
  "1041": "\t黒王の斥力波\r",
  "1042": "\t復讐の誓い\r",
  "1043": "\t氷雷剣\r",
  "1044": "\t獣王の爪\r",
  "1045": "\t炎の舞\r",
  "1046": "\t爪弾き\r",
  "1047": "\t星雲\r",
  "1048": "\t霊炎発火\r",
  "1049": "\t古雷の槍\r",
  "1050": "\t狂い火突き\r",
  "1051": "\tミケラの光輪\r",
  "1052": "\t黄金の剣技\r",
  "1053": "\t弔いの墓標\r",
  "1054": "\t防ぎ得ぬ刃\r",
  "1055": "\tエオヒドの剣舞\r",
  "1167": "\t死蝋斬り\r",
  "1168": "\tザミェルの氷嵐\r",
  "1169": "\tラダーンの驟雨\r",
  "1170": "\t女王の黒炎\r",
  "1171": "\t王朝剣技\r",
  "1172": "\t溶岩撒き\r",
  "1173": "\t星雲\r",
  "1174": "\t死のフレア\r",
  "1175": "\t猟犬の剣技\r",
  "1176": "\t溶岩ギロチン\r",
  "1177": "\t死屍累々\r",
  "1178": "\t束の間の月影\r",
  "1179": "\t血刃乱舞\r",
  "1180": "\t死蝶の舞\r",
  "1181": "\tミケラの秘剣\r",
  "1182": "\t百智の世界\r",
  "1183": "\t世界喰らい\r",
  "1184": "\t家族の怨霊\r",
  "1185": "\tローゼスの呼び声\r",
  "1186": "\t雷嵐\r",
  "1187": "\t聖槍の壁\r",
  "1188": "\t大蛇狩り\r",
  "1189": "\t天使の翼\r",
  "1190": "\t嵐蹴撃\r",
  "1191": "\t防ぎ得ぬ刃\r",
  "1192": "\t錫杖の魔術\r",
  "1193": "\t黄金樹の尻撃\r",
  "1194": "\t重力雷\r",
  "1195": "\t眠りの炎\r",
  "1196": "\t黄金の返報\r",
  "1197": "\t伝染する怒り\r",
  "1198": "\tオルドビスの渦\r",
  "1199": "\t回れ回れ\r",
  "": ""
}
